{
    "author": "Góngora, Luis de",
    "authorship": "segura",
    "incipit": "La vidrïera mejor",
    "year": "1615",
    "text": "La vidrïera mejor\nen sus brazos de cristal\nentra al Sol, hoy, celestial\nen la capilla mayor,\na cuyo resplandor,\nsin que más luz espere,\nSimeón fénix arde y cisne muere.",
    "scanned_poem": [
        {
            "tokens": [
                {
                    "word": [
                        {
                            "syllable": "La",
                            "is_stressed": false,
                            "is_word_end": true
                        }
                    ],
                    "stress_position": 0
                },
                {
                    "word": [
                        {
                            "syllable": "vid",
                            "is_stressed": false
                        },
                        {
                            "syllable": "rï",
                            "is_stressed": false
                        },
                        {
                            "syllable": "e",
                            "is_stressed": true
                        },
                        {
                            "syllable": "ra",
                            "is_stressed": false,
                            "is_word_end": true
                        }
                    ],
                    "stress_position": -2
                },
                {
                    "word": [
                        {
                            "syllable": "me",
                            "is_stressed": false
                        },
                        {
                            "syllable": "jor",
                            "is_stressed": true,
                            "is_word_end": true
                        }
                    ],
                    "stress_position": -1
                }
            ],
            "phonological_groups": [
                {
                    "syllable": "La",
                    "is_stressed": false,
                    "is_word_end": true
                },
                {
                    "syllable": "vid",
                    "is_stressed": false
                },
                {
                    "syllable": "rï",
                    "is_stressed": false
                },
                {
                    "syllable": "e",
                    "is_stressed": true
                },
                {
                    "syllable": "ra",
                    "is_stressed": false,
                    "is_word_end": true
                },
                {
                    "syllable": "me",
                    "is_stressed": false
                },
                {
                    "syllable": "jor",
                    "is_stressed": true,
                    "is_word_end": true
                }
            ],
            "rhythm": {
                "stress": "---+--+-",
                "type": "pattern",
                "length": 8
            }
        },
        {
            "tokens": [
                {
                    "word": [
                        {
                            "syllable": "en",
                            "is_stressed": false,
                            "is_word_end": true
                        }
                    ],
                    "stress_position": 0
                },
                {
                    "word": [
                        {
                            "syllable": "sus",
                            "is_stressed": false,
                            "is_word_end": true
                        }
                    ],
                    "stress_position": 0
                },
                {
                    "word": [
                        {
                            "syllable": "bra",
                            "is_stressed": true
                        },
                        {
                            "syllable": "zos",
                            "is_stressed": false,
                            "is_word_end": true
                        }
                    ],
                    "stress_position": -2
                },
                {
                    "word": [
                        {
                            "syllable": "de",
                            "is_stressed": false,
                            "is_word_end": true
                        }
                    ],
                    "stress_position": 0
                },
                {
                    "word": [
                        {
                            "syllable": "cris",
                            "is_stressed": false
                        },
                        {
                            "syllable": "tal",
                            "is_stressed": true,
                            "is_word_end": true
                        }
                    ],
                    "stress_position": -1
                }
            ],
            "phonological_groups": [
                {
                    "syllable": "en",
                    "is_stressed": false,
                    "is_word_end": true
                },
                {
                    "syllable": "sus",
                    "is_stressed": false,
                    "is_word_end": true
                },
                {
                    "syllable": "bra",
                    "is_stressed": true
                },
                {
                    "syllable": "zos",
                    "is_stressed": false,
                    "is_word_end": true
                },
                {
                    "syllable": "de",
                    "is_stressed": false,
                    "is_word_end": true
                },
                {
                    "syllable": "cris",
                    "is_stressed": false
                },
                {
                    "syllable": "tal",
                    "is_stressed": true,
                    "is_word_end": true
                }
            ],
            "rhythm": {
                "stress": "--+---+-",
                "type": "pattern",
                "length": 8
            }
        },
        {
            "tokens": [
                {
                    "word": [
                        {
                            "syllable": "en",
                            "is_stressed": true
                        },
                        {
                            "syllable": "tra",
                            "is_stressed": false,
                            "has_synalepha": true,
                            "is_word_end": true
                        }
                    ],
                    "stress_position": -2
                },
                {
                    "word": [
                        {
                            "syllable": "al",
                            "is_stressed": false,
                            "is_word_end": true
                        }
                    ],
                    "stress_position": 0
                },
                {
                    "word": [
                        {
                            "syllable": "Sol",
                            "is_stressed": true,
                            "is_word_end": true
                        }
                    ],
                    "stress_position": -1
                },
                {
                    "symbol": ","
                },
                {
                    "word": [
                        {
                            "syllable": "hoy",
                            "is_stressed": true,
                            "is_word_end": true
                        }
                    ],
                    "stress_position": -1
                },
                {
                    "symbol": ","
                },
                {
                    "word": [
                        {
                            "syllable": "ce",
                            "is_stressed": false
                        },
                        {
                            "syllable": "les",
                            "is_stressed": false
                        },
                        {
                            "syllable": "tial",
                            "is_stressed": true,
                            "is_word_end": true
                        }
                    ],
                    "stress_position": -1
                }
            ],
            "phonological_groups": [
                {
                    "syllable": "en",
                    "is_stressed": true
                },
                {
                    "syllable": "traal",
                    "is_stressed": false,
                    "synalepha_index": [
                        2
                    ],
                    "is_word_end": true
                },
                {
                    "syllable": "Sol",
                    "is_stressed": true,
                    "is_word_end": true
                },
                {
                    "syllable": "hoy",
                    "is_stressed": true,
                    "is_word_end": true
                },
                {
                    "syllable": "ce",
                    "is_stressed": false
                },
                {
                    "syllable": "les",
                    "is_stressed": false
                },
                {
                    "syllable": "tial",
                    "is_stressed": true,
                    "is_word_end": true
                }
            ],
            "rhythm": {
                "stress": "+-++--+-",
                "type": "pattern",
                "length": 8
            }
        },
        {
            "tokens": [
                {
                    "word": [
                        {
                            "syllable": "en",
                            "is_stressed": false,
                            "is_word_end": true
                        }
                    ],
                    "stress_position": 0
                },
                {
                    "word": [
                        {
                            "syllable": "la",
                            "is_stressed": false,
                            "is_word_end": true
                        }
                    ],
                    "stress_position": 0
                },
                {
                    "word": [
                        {
                            "syllable": "ca",
                            "is_stressed": false
                        },
                        {
                            "syllable": "pi",
                            "is_stressed": true
                        },
                        {
                            "syllable": "lla",
                            "is_stressed": false,
                            "is_word_end": true
                        }
                    ],
                    "stress_position": -2
                },
                {
                    "word": [
                        {
                            "syllable": "ma",
                            "is_stressed": false
                        },
                        {
                            "syllable": "yor",
                            "is_stressed": true,
                            "is_word_end": true
                        }
                    ],
                    "stress_position": -1
                },
                {
                    "symbol": ","
                }
            ],
            "phonological_groups": [
                {
                    "syllable": "en",
                    "is_stressed": false,
                    "is_word_end": true
                },
                {
                    "syllable": "la",
                    "is_stressed": false,
                    "is_word_end": true
                },
                {
                    "syllable": "ca",
                    "is_stressed": false
                },
                {
                    "syllable": "pi",
                    "is_stressed": true
                },
                {
                    "syllable": "lla",
                    "is_stressed": false,
                    "is_word_end": true
                },
                {
                    "syllable": "ma",
                    "is_stressed": false
                },
                {
                    "syllable": "yor",
                    "is_stressed": true,
                    "is_word_end": true
                }
            ],
            "rhythm": {
                "stress": "---+--+-",
                "type": "pattern",
                "length": 8
            }
        },
        {
            "tokens": [
                {
                    "word": [
                        {
                            "syllable": "a",
                            "is_stressed": false,
                            "is_word_end": true
                        }
                    ],
                    "stress_position": 0
                },
                {
                    "word": [
                        {
                            "syllable": "cu",
                            "is_stressed": false
                        },
                        {
                            "syllable": "yo",
                            "is_stressed": false,
                            "is_word_end": true
                        }
                    ],
                    "stress_position": 0
                },
                {
                    "word": [
                        {
                            "syllable": "res",
                            "is_stressed": false
                        },
                        {
                            "syllable": "plan",
                            "is_stressed": false
                        },
                        {
                            "syllable": "dor",
                            "is_stressed": true,
                            "is_word_end": true
                        }
                    ],
                    "stress_position": -1
                },
                {
                    "symbol": ","
                }
            ],
            "phonological_groups": [
                {
                    "syllable": "a",
                    "is_stressed": false,
                    "is_word_end": true
                },
                {
                    "syllable": "cu",
                    "is_stressed": false
                },
                {
                    "syllable": "yo",
                    "is_stressed": false,
                    "is_word_end": true
                },
                {
                    "syllable": "res",
                    "is_stressed": false
                },
                {
                    "syllable": "plan",
                    "is_stressed": false
                },
                {
                    "syllable": "dor",
                    "is_stressed": true,
                    "is_word_end": true
                }
            ],
            "rhythm": {
                "stress": "-----+-",
                "type": "pattern",
                "length": 7
            }
        },
        {
            "tokens": [
                {
                    "word": [
                        {
                            "syllable": "sin",
                            "is_stressed": false,
                            "is_word_end": true
                        }
                    ],
                    "stress_position": 0
                },
                {
                    "word": [
                        {
                            "syllable": "que",
                            "is_stressed": false,
                            "is_word_end": true
                        }
                    ],
                    "stress_position": 0
                },
                {
                    "word": [
                        {
                            "syllable": "más",
                            "is_stressed": true,
                            "is_word_end": true
                        }
                    ],
                    "stress_position": -1
                },
                {
                    "word": [
                        {
                            "syllable": "luz",
                            "is_stressed": true,
                            "is_word_end": true
                        }
                    ],
                    "stress_position": -1
                },
                {
                    "word": [
                        {
                            "syllable": "es",
                            "is_stressed": false
                        },
                        {
                            "syllable": "pe",
                            "is_stressed": true
                        },
                        {
                            "syllable": "re",
                            "is_stressed": false,
                            "is_word_end": true
                        }
                    ],
                    "stress_position": -2
                },
                {
                    "symbol": ","
                }
            ],
            "phonological_groups": [
                {
                    "syllable": "sin",
                    "is_stressed": false,
                    "is_word_end": true
                },
                {
                    "syllable": "que",
                    "is_stressed": false,
                    "is_word_end": true
                },
                {
                    "syllable": "más",
                    "is_stressed": true,
                    "is_word_end": true
                },
                {
                    "syllable": "luz",
                    "is_stressed": true,
                    "is_word_end": true
                },
                {
                    "syllable": "es",
                    "is_stressed": false
                },
                {
                    "syllable": "pe",
                    "is_stressed": true
                },
                {
                    "syllable": "re",
                    "is_stressed": false,
                    "is_word_end": true
                }
            ],
            "rhythm": {
                "stress": "--++-+-",
                "type": "pattern",
                "length": 7
            }
        },
        {
            "tokens": [
                {
                    "word": [
                        {
                            "syllable": "Si",
                            "is_stressed": false
                        },
                        {
                            "syllable": "me",
                            "is_stressed": false,
                            "has_sinaeresis": true
                        },
                        {
                            "syllable": "ón",
                            "is_stressed": true,
                            "is_word_end": true
                        }
                    ],
                    "stress_position": -1
                },
                {
                    "word": [
                        {
                            "syllable": "fé",
                            "is_stressed": true
                        },
                        {
                            "syllable": "nix",
                            "is_stressed": false,
                            "is_word_end": true
                        }
                    ],
                    "stress_position": -2
                },
                {
                    "word": [
                        {
                            "syllable": "ar",
                            "is_stressed": true
                        },
                        {
                            "syllable": "de",
                            "is_stressed": false,
                            "has_synalepha": true,
                            "is_word_end": true
                        }
                    ],
                    "stress_position": -2
                },
                {
                    "word": [
                        {
                            "syllable": "y",
                            "is_stressed": false,
                            "is_word_end": true
                        }
                    ],
                    "stress_position": 0
                },
                {
                    "word": [
                        {
                            "syllable": "cis",
                            "is_stressed": true
                        },
                        {
                            "syllable": "ne",
                            "is_stressed": false,
                            "is_word_end": true
                        }
                    ],
                    "stress_position": -2
                },
                {
                    "word": [
                        {
                            "syllable": "mue",
                            "is_stressed": true
                        },
                        {
                            "syllable": "re",
                            "is_stressed": false,
                            "is_word_end": true
                        }
                    ],
                    "stress_position": -2
                },
                {
                    "symbol": "."
                }
            ],
            "phonological_groups": [
                {
                    "syllable": "Si",
                    "is_stressed": false
                },
                {
                    "syllable": "meón",
                    "is_stressed": true,
                    "sinaeresis_index": [
                        1
                    ],
                    "is_word_end": true
                },
                {
                    "syllable": "fé",
                    "is_stressed": true
                },
                {
                    "syllable": "nix",
                    "is_stressed": false,
                    "is_word_end": true
                },
                {
                    "syllable": "ar",
                    "is_stressed": true
                },
                {
                    "syllable": "dey",
                    "is_stressed": false,
                    "synalepha_index": [
                        1
                    ],
                    "is_word_end": true
                },
                {
                    "syllable": "cis",
                    "is_stressed": true
                },
                {
                    "syllable": "ne",
                    "is_stressed": false,
                    "is_word_end": true
                },
                {
                    "syllable": "mue",
                    "is_stressed": true
                },
                {
                    "syllable": "re",
                    "is_stressed": false,
                    "is_word_end": true
                }
            ],
            "rhythm": {
                "stress": "-++-+-+-+-",
                "type": "pattern",
                "length": 10
            }
        }
    ]
}